[{"date":"Tue, 06 Aug 2013 04:13:09 GMT","total":{"sloc":162,"maintainability":65.11075601309322},"average":{"sloc":162,"maintainability":"65.11"}},{"date":"Wed, 07 Aug 2013 17:24:22 GMT","total":{"sloc":169,"maintainability":64.82480856373849},"average":{"sloc":169,"maintainability":"64.82"}},{"date":"Wed, 07 Aug 2013 19:18:07 GMT","total":{"sloc":166,"maintainability":65.01141011959797},"average":{"sloc":166,"maintainability":"65.01"}},{"date":"Thu, 08 Aug 2013 03:50:12 GMT","total":{"sloc":168,"maintainability":65.26406773714172},"average":{"sloc":168,"maintainability":"65.26"}},{"date":"Fri, 09 Aug 2013 14:38:29 GMT","total":{"sloc":175,"maintainability":66.42645910352832},"average":{"sloc":175,"maintainability":"66.43"}},{"date":"Fri, 09 Aug 2013 19:16:47 GMT","total":{"sloc":188,"maintainability":65.67366920011602},"average":{"sloc":188,"maintainability":"65.67"}},{"date":"Fri, 09 Aug 2013 21:37:10 GMT","total":{"sloc":185,"maintainability":64.96869230889651},"average":{"sloc":185,"maintainability":"64.97"}},{"date":"Sun, 11 Aug 2013 16:16:44 GMT","total":{"sloc":228,"maintainability":63.315211607376156},"average":{"sloc":228,"maintainability":"63.32"}}]